mjcf2usd/__init__.py
mjcf2usd-0.0.1.dist-info/METADATA
mjcf2usd-0.0.1.dist-info/WHEEL
mjcf2usd-0.0.1.dist-info/top_level.txt
mjcf2usd-0.0.1.dist-info/RECORD
